pozetron_cli-0.8.0.data/scripts/poze.py
pozetroncli/__init__.py
pozetroncli/cache.py
pozetroncli/commands.py
pozetroncli/conf.py
pozetroncli/digest.py
pozetroncli/error.py
pozetroncli/log.py
pozetroncli/main.py
pozetroncli/tags.py
pozetroncli/utils.py
pozetron_cli-0.8.0.dist-info/METADATA
pozetron_cli-0.8.0.dist-info/WHEEL
pozetron_cli-0.8.0.dist-info/top_level.txt
pozetron_cli-0.8.0.dist-info/zip-safe
pozetron_cli-0.8.0.dist-info/RECORD
