Metadata-Version: 2.1
Name: pozetron-cli
Version: 0.8.0
Summary: Pozetron command-line interface. The developer interface for the Pozetron IoT Cloud.
Home-page: https://www.pozetron.com
Author: Pozetron Inc
Author-email: hello@pozetroninc.com
License: Apache License 2.0
Keywords: pozetron,IoT,MicroPython
Platform: UNKNOWN
Classifier: Development Status :: 5 - Production/Stable
Classifier: Environment :: Console
Classifier: Intended Audience :: Developers
Classifier: Programming Language :: Python
Classifier: Programming Language :: Python :: 3
Requires-Dist: certifi (==2020.4.5.1)
Requires-Dist: chardet (==3.0.4)
Requires-Dist: dictdiffer (==0.7.1)
Requires-Dist: httpsig-pure-hmac (==1.1.2)
Requires-Dist: idna (==2.9)
Requires-Dist: pydicti (==0.0.6)
Requires-Dist: python-dateutil (==2.8.1)
Requires-Dist: pytz (==2016.10)
Requires-Dist: requests (==2.23.0)
Requires-Dist: six (==1.15.0)
Requires-Dist: urllib3 (==1.25.9)
